gymnasdicts/__init__.py
gymnasdicts/base.py
gymnasdicts/utils.py
gymnasdicts-0.1.2.dist-info/AUTHORS.rst
gymnasdicts-0.1.2.dist-info/LICENSE
gymnasdicts-0.1.2.dist-info/METADATA
gymnasdicts-0.1.2.dist-info/WHEEL
gymnasdicts-0.1.2.dist-info/top_level.txt
gymnasdicts-0.1.2.dist-info/RECORD
