Metadata-Version: 2.1
Name: gymnasdicts
Version: 0.1.2
Summary: query json dicts
Home-page: https://github.com/unai/gymnasdicts
Author: George Burton
Author-email: george.burton@unai.com
License: Apache Software License 2.0
Keywords: gymnasdicts
Platform: UNKNOWN
Classifier: Development Status :: 2 - Pre-Alpha
Classifier: Intended Audience :: Developers
Classifier: License :: OSI Approved :: Apache Software License
Classifier: Natural Language :: English
Classifier: Programming Language :: Python :: 3
Classifier: Programming Language :: Python :: 3.7
Classifier: Programming Language :: Python :: 3.8
Requires-Python: >=3.7
Requires-Dist: jsonpath-ng (>=1.5)
